qiskit_class_converter/__init__.py
qiskit_class_converter/converters/__init__.py
qiskit_class_converter/converters/base.py
qiskit_class_converter/converters/matrix_to_quantum_circuit.py
qiskit_class_converter/converters/quantum_circuit_to_braket_notation.py
qiskit_class_converter/converters/quantum_circuit_to_matrix.py
qiskit_class_converter/converters/string_to_braket_notation.py
qiskit_class_converter/services/__init__.py
qiskit_class_converter/services/converter_service.py
qiskit_classroom_converter-0.6.0.dist-info/LICENSE
qiskit_classroom_converter-0.6.0.dist-info/METADATA
qiskit_classroom_converter-0.6.0.dist-info/WHEEL
qiskit_classroom_converter-0.6.0.dist-info/top_level.txt
qiskit_classroom_converter-0.6.0.dist-info/RECORD
