Metadata-Version: 2.1
Name: qiskit-classroom-converter
Version: 0.6.0
Summary: extend the Qiskit classroom applications.
Author: KMU-quantum-classroom
Project-URL: Homepage, https://github.com/KMU-quantum-classroom/qiskit-classroom-converter
Project-URL: Bug Tracker, https://github.com/KMU-quantum-classroom/qiskit-classroom-converter/issues
Classifier: Programming Language :: Python :: 3
Classifier: License :: OSI Approved :: Apache Software License
Classifier: Operating System :: OS Independent
Requires-Python: >=3.10
License-File: LICENSE
Requires-Dist: qiskit==1.3.1
Requires-Dist: qiskit-aer==0.15.1
Requires-Dist: loguru==0.7.3
Requires-Dist: sympy==1.13.3
Requires-Dist: antlr4-python3-runtime==4.11
Requires-Dist: ipython==8.31.0
Requires-Dist: numpy==2.2.1
Provides-Extra: dev
Requires-Dist: coverage==7.6.10; extra == "dev"
Requires-Dist: pylint==3.3.3; extra == "dev"
Requires-Dist: tox==4.23.2; extra == "dev"
Requires-Dist: build==1.2.2.post1; extra == "dev"
Requires-Dist: pdoc==15.0.1; extra == "dev"
Requires-Dist: notebook==7.3.2; extra == "dev"
